mgt7_pdf_to_json/__init__.py
mgt7_pdf_to_json/__main__.py
mgt7_pdf_to_json/artifacts.py
mgt7_pdf_to_json/cli.py
mgt7_pdf_to_json/config.py
mgt7_pdf_to_json/date_utils.py
mgt7_pdf_to_json/exceptions.py
mgt7_pdf_to_json/extractor.py
mgt7_pdf_to_json/logging_.py
mgt7_pdf_to_json/mappers.py
mgt7_pdf_to_json/models.py
mgt7_pdf_to_json/normalizer.py
mgt7_pdf_to_json/parser.py
mgt7_pdf_to_json/pipeline.py
mgt7_pdf_to_json/validator.py
mgt7_pdf_to_json-0.1.9.dist-info/licenses/LICENSE
mgt7_pdf_to_json-0.1.9.dist-info/METADATA
mgt7_pdf_to_json-0.1.9.dist-info/WHEEL
mgt7_pdf_to_json-0.1.9.dist-info/entry_points.txt
mgt7_pdf_to_json-0.1.9.dist-info/top_level.txt
mgt7_pdf_to_json-0.1.9.dist-info/RECORD
