Metadata-Version: 2.4
Name: mgt7-pdf-to-json
Version: 0.1.9
Summary: Convert India MCA annual return PDF forms MGT-7 and MGT-7A into structured JSON
Author: Valerii Kholodilin
License: MIT
Keywords: pdf,mgt7,mgt7a,json,parser,india,mca
Classifier: Development Status :: 3 - Alpha
Classifier: Intended Audience :: Developers
Classifier: License :: OSI Approved :: MIT License
Classifier: Programming Language :: Python :: 3
Classifier: Programming Language :: Python :: 3.9
Classifier: Programming Language :: Python :: 3.10
Classifier: Programming Language :: Python :: 3.11
Classifier: Programming Language :: Python :: 3.12
Classifier: Programming Language :: Python :: 3.13
Requires-Python: >=3.9
License-File: LICENSE
Requires-Dist: pdfplumber>=0.10.0
Requires-Dist: pyyaml>=6.0
Requires-Dist: pydantic>=2.0.0
Provides-Extra: dev
Requires-Dist: pytest>=7.4.0; extra == "dev"
Requires-Dist: pytest-cov>=4.1.0; extra == "dev"
Requires-Dist: ruff>=0.1.0; extra == "dev"
Requires-Dist: mypy>=1.5.0; extra == "dev"
Requires-Dist: types-pyyaml>=6.0.0; extra == "dev"
Requires-Dist: black>=23.0.0; extra == "dev"
Requires-Dist: safety>=2.3.0; extra == "dev"
Requires-Dist: bandit[toml]>=1.7.0; extra == "dev"
Dynamic: license-file
